trtimeextractor/__init__.py
trtimeextractor/config.py
trtimeextractor/extractor.py
trtimeextractor-0.1.2.dist-info/METADATA
trtimeextractor-0.1.2.dist-info/WHEEL
trtimeextractor-0.1.2.dist-info/top_level.txt
trtimeextractor-0.1.2.dist-info/RECORD
