Metadata-Version: 2.1
Name: trtimeextractor
Version: 0.1.2
Summary: Time Extractor NLP project - locate dates and times in text documents
Home-page: https://github.com/westeropsml/time-extractor-tr
Author: WesterOps
Author-email: ml@westerops.com
License: WesterOps
Keywords: NLP text extraction time date
Requires-Dist: pyjnius (==1.1.1)
